[
  {
    "id": 0,
    "name": "bamboo_jungle",
    "category": "bamboo",
    "temperature": 0.949999988079071,
    "has_percipitation": true,
    "dimension": "overworld",
    "displayName": "bamboo_jungle",
    "color": 1352389
  },
  {
    "id": 1,
    "name": "bamboo_jungle_hills",
    "category": "bamboo",
    "temperature": 0.949999988079071,
    "has_percipitation": true,
    "dimension": "overworld",
    "displayName": "bamboo_jungle_hills",
    "color": 1810136
  },
  {
    "id": 2,
    "name": "basalt_deltas",
    "category": "nether",
    "temperature": 2,
    "has_percipitation": false,
    "dimension": "nether",
    "displayName": "basalt_deltas",
    "color": 4159204
  },
  {
    "id": 3,
    "name": "beach",
    "category": "beach",
    "temperature": 0.800000011920929,
    "has_percipitation": true,
    "dimension": "overworld",
    "displayName": "beach",
    "color": 1408171
  },
  {
    "id": 4,
    "name": "birch_forest",
    "category": "birch",
    "temperature": 0.6000000238418579,
    "has_percipitation": true,
    "dimension": "overworld",
    "displayName": "birch_forest",
    "color": 423886
  },
  {
    "id": 5,
    "name": "birch_forest_hills",
    "category": "birch",
    "temperature": 0.6000000238418579,
    "has_percipitation": true,
    "dimension": "overworld",
    "displayName": "birch_forest_hills",
    "color": 685252
  },
  {
    "id": 6,
    "name": "birch_forest_hills_mutated",
    "category": "birch",
    "temperature": 0.699999988079071,
    "has_percipitation": true,
    "dimension": "overworld",
    "displayName": "birch_forest_hills_mutated",
    "color": 685252
  },
  {
    "id": 7,
    "name": "birch_forest_mutated",
    "category": "birch",
    "temperature": 0.6000000238418579,
    "has_percipitation": true,
    "dimension": "overworld",
    "displayName": "birch_forest_mutated",
    "color": 423886
  },
  {
    "id": 8,
    "name": "cherry_grove",
    "category": "mountains",
    "temperature": 0.30000001192092896,
    "has_percipitation": true,
    "dimension": "overworld",
    "displayName": "cherry_grove",
    "color": 6338559
  },
  {
    "id": 9,
    "name": "cold_beach",
    "category": "beach",
    "temperature": 0.05000000074505806,
    "has_percipitation": true,
    "dimension": "overworld",
    "displayName": "cold_beach",
    "color": 1336229
  },
  {
    "id": 10,
    "name": "cold_ocean",
    "category": "cold",
    "temperature": 0.5,
    "has_percipitation": true,
    "dimension": "overworld",
    "displayName": "cold_ocean",
    "color": 2130121
  },
  {
    "id": 11,
    "name": "cold_taiga",
    "category": "cold",
    "temperature": -0.5,
    "has_percipitation": true,
    "dimension": "overworld",
    "displayName": "cold_taiga",
    "color": 2121347
  },
  {
    "id": 12,
    "name": "cold_taiga_hills",
    "category": "cold",
    "temperature": -0.5,
    "has_percipitation": true,
    "dimension": "overworld",
    "displayName": "cold_taiga_hills",
    "color": 2382712
  },
  {
    "id": 13,
    "name": "cold_taiga_mutated",
    "category": "cold",
    "temperature": -0.5,
    "has_percipitation": true,
    "dimension": "overworld",
    "displayName": "cold_taiga_mutated",
    "color": 2121347
  },
  {
    "id": 14,
    "name": "crimson_forest",
    "category": "nether",
    "temperature": 2,
    "has_percipitation": false,
    "dimension": "nether",
    "displayName": "crimson_forest",
    "color": 9460055
  },
  {
    "id": 15,
    "name": "deep_cold_ocean",
    "category": "cold",
    "temperature": 0.5,
    "has_percipitation": true,
    "dimension": "overworld",
    "displayName": "deep_cold_ocean",
    "color": 2130121
  },
  {
    "id": 16,
    "name": "deep_dark",
    "category": "caves",
    "temperature": 0.800000011920929,
    "has_percipitation": true,
    "dimension": "overworld",
    "displayName": "deep_dark",
    "color": 6338559
  },
  {
    "id": 17,
    "name": "deep_frozen_ocean",
    "category": "deep",
    "temperature": 0,
    "has_percipitation": true,
    "dimension": "overworld",
    "displayName": "deep_frozen_ocean",
    "color": 2453685
  },
  {
    "id": 18,
    "name": "deep_lukewarm_ocean",
    "category": "deep",
    "temperature": 0.5,
    "has_percipitation": true,
    "dimension": "overworld",
    "displayName": "deep_lukewarm_ocean",
    "color": 890587
  },
  {
    "id": 19,
    "name": "deep_ocean",
    "category": "deep",
    "temperature": 0.5,
    "has_percipitation": true,
    "dimension": "overworld",
    "displayName": "deep_ocean",
    "color": 1542100
  },
  {
    "id": 20,
    "name": "deep_warm_ocean",
    "category": "deep",
    "temperature": 0.5,
    "has_percipitation": true,
    "dimension": "overworld",
    "displayName": "deep_warm_ocean",
    "color": 176357
  },
  {
    "id": 21,
    "name": "desert",
    "category": "desert",
    "temperature": 2,
    "has_percipitation": false,
    "dimension": "overworld",
    "displayName": "desert",
    "color": 3319192
  },
  {
    "id": 22,
    "name": "desert_hills",
    "category": "desert",
    "temperature": 2,
    "has_percipitation": false,
    "dimension": "overworld",
    "displayName": "desert_hills",
    "color": 1735329
  },
  {
    "id": 23,
    "name": "desert_mutated",
    "category": "desert",
    "temperature": 2,
    "has_percipitation": false,
    "dimension": "overworld",
    "displayName": "desert_mutated",
    "color": 3319192
  },
  {
    "id": 24,
    "name": "dripstone_caves",
    "category": "caves",
    "temperature": 0.20000000298023224,
    "has_percipitation": true,
    "dimension": "overworld",
    "displayName": "dripstone_caves",
    "color": 6338559
  },
  {
    "id": 25,
    "name": "extreme_hills",
    "category": "extreme_hills",
    "temperature": 0.20000000298023224,
    "has_percipitation": true,
    "dimension": "overworld",
    "displayName": "extreme_hills",
    "color": 31735
  },
  {
    "id": 26,
    "name": "extreme_hills_edge",
    "category": "edge",
    "temperature": 0.20000000298023224,
    "has_percipitation": true,
    "dimension": "overworld",
    "displayName": "extreme_hills_edge",
    "color": 285909
  },
  {
    "id": 27,
    "name": "extreme_hills_mutated",
    "category": "extreme_hills",
    "temperature": 0.20000000298023224,
    "has_percipitation": true,
    "dimension": "overworld",
    "displayName": "extreme_hills_mutated",
    "color": 943019
  },
  {
    "id": 28,
    "name": "extreme_hills_plus_trees",
    "category": "extreme_hills",
    "temperature": 0.20000000298023224,
    "has_percipitation": true,
    "dimension": "overworld",
    "displayName": "extreme_hills_plus_trees",
    "color": 943019
  },
  {
    "id": 29,
    "name": "extreme_hills_plus_trees_mutated",
    "category": "extreme_hills",
    "temperature": 0.20000000298023224,
    "has_percipitation": true,
    "dimension": "overworld",
    "displayName": "extreme_hills_plus_trees_mutated",
    "color": 943019
  },
  {
    "id": 30,
    "name": "flower_forest",
    "category": "flower_forest",
    "temperature": 0.699999988079071,
    "has_percipitation": true,
    "dimension": "overworld",
    "displayName": "flower_forest",
    "color": 2139084
  },
  {
    "id": 31,
    "name": "forest",
    "category": "forest",
    "temperature": 0.699999988079071,
    "has_percipitation": true,
    "dimension": "overworld",
    "displayName": "forest",
    "color": 2004978
  },
  {
    "id": 32,
    "name": "forest_hills",
    "category": "hills",
    "temperature": 0.699999988079071,
    "has_percipitation": true,
    "dimension": "overworld",
    "displayName": "forest_hills",
    "color": 355281
  },
  {
    "id": 33,
    "name": "frozen_ocean",
    "category": "frozen",
    "temperature": 0,
    "has_percipitation": true,
    "dimension": "overworld",
    "displayName": "frozen_ocean",
    "color": 2453685
  },
  {
    "id": 34,
    "name": "frozen_peaks",
    "category": "mountains",
    "temperature": -0.699999988079071,
    "has_percipitation": true,
    "dimension": "overworld",
    "displayName": "frozen_peaks",
    "color": 6338559
  },
  {
    "id": 35,
    "name": "frozen_river",
    "category": "frozen",
    "temperature": 0,
    "has_percipitation": true,
    "dimension": "overworld",
    "displayName": "frozen_river",
    "color": 1594256
  },
  {
    "id": 36,
    "name": "grove",
    "category": "mountains",
    "temperature": -0.20000000298023224,
    "has_percipitation": true,
    "dimension": "overworld",
    "displayName": "grove",
    "color": 6338559
  },
  {
    "id": 37,
    "name": "hell",
    "category": "nether",
    "temperature": 2,
    "has_percipitation": false,
    "dimension": "nether",
    "displayName": "hell",
    "color": 9460055
  },
  {
    "id": 38,
    "name": "ice_mountains",
    "category": "frozen",
    "temperature": 0,
    "has_percipitation": true,
    "dimension": "overworld",
    "displayName": "ice_mountains",
    "color": 1136295
  },
  {
    "id": 39,
    "name": "ice_plains",
    "category": "frozen",
    "temperature": 0,
    "has_percipitation": true,
    "dimension": "overworld",
    "displayName": "ice_plains",
    "color": 1332635
  },
  {
    "id": 40,
    "name": "ice_plains_spikes",
    "category": "frozen",
    "temperature": 0,
    "has_percipitation": true,
    "dimension": "overworld",
    "displayName": "ice_plains_spikes",
    "color": 6338559
  },
  {
    "id": 41,
    "name": "jagged_peaks",
    "category": "mountains",
    "temperature": -0.699999988079071,
    "has_percipitation": true,
    "dimension": "overworld",
    "displayName": "jagged_peaks",
    "color": 6338559
  },
  {
    "id": 42,
    "name": "jungle",
    "category": "has_structure_trail_ruins",
    "temperature": 0.949999988079071,
    "has_percipitation": true,
    "dimension": "overworld",
    "displayName": "jungle",
    "color": 1352389
  },
  {
    "id": 43,
    "name": "jungle_edge",
    "category": "edge",
    "temperature": 0.949999988079071,
    "has_percipitation": true,
    "dimension": "overworld",
    "displayName": "jungle_edge",
    "color": 887523
  },
  {
    "id": 44,
    "name": "jungle_edge_mutated",
    "category": "edge",
    "temperature": 0.949999988079071,
    "has_percipitation": true,
    "dimension": "overworld",
    "displayName": "jungle_edge_mutated",
    "color": 887523
  },
  {
    "id": 45,
    "name": "jungle_hills",
    "category": "hills",
    "temperature": 0.949999988079071,
    "has_percipitation": true,
    "dimension": "overworld",
    "displayName": "jungle_hills",
    "color": 1810136
  },
  {
    "id": 46,
    "name": "jungle_mutated",
    "category": "jungle",
    "temperature": 0.949999988079071,
    "has_percipitation": true,
    "dimension": "overworld",
    "displayName": "jungle_mutated",
    "color": 1810136
  },
  {
    "id": 47,
    "name": "legacy_frozen_ocean",
    "category": "legacy",
    "temperature": 0,
    "has_percipitation": true,
    "dimension": "overworld",
    "displayName": "legacy_frozen_ocean",
    "color": 6338559
  },
  {
    "id": 48,
    "name": "lukewarm_ocean",
    "category": "lukewarm",
    "temperature": 0.5,
    "has_percipitation": true,
    "dimension": "overworld",
    "displayName": "lukewarm_ocean",
    "color": 890587
  },
  {
    "id": 49,
    "name": "lush_caves",
    "category": "caves",
    "temperature": 0.8999999761581421,
    "has_percipitation": true,
    "dimension": "overworld",
    "displayName": "lush_caves",
    "color": 6338559
  },
  {
    "id": 50,
    "name": "mangrove_swamp",
    "category": "mangrove_swamp",
    "temperature": 0.800000011920929,
    "has_percipitation": true,
    "dimension": "overworld",
    "displayName": "mangrove_swamp",
    "color": 6338559
  },
  {
    "id": 51,
    "name": "meadow",
    "category": "mountains",
    "temperature": 0.30000001192092896,
    "has_percipitation": true,
    "dimension": "overworld",
    "displayName": "meadow",
    "color": 6338559
  },
  {
    "id": 52,
    "name": "mega_taiga",
    "category": "forest",
    "temperature": 0.30000001192092896,
    "has_percipitation": true,
    "dimension": "overworld",
    "displayName": "mega_taiga",
    "color": 2977143
  },
  {
    "id": 53,
    "name": "mega_taiga_hills",
    "category": "forest",
    "temperature": 0.30000001192092896,
    "has_percipitation": true,
    "dimension": "overworld",
    "displayName": "mega_taiga_hills",
    "color": 2646904
  },
  {
    "id": 54,
    "name": "mesa",
    "category": "mesa",
    "temperature": 2,
    "has_percipitation": false,
    "dimension": "overworld",
    "displayName": "mesa",
    "color": 5144449
  },
  {
    "id": 55,
    "name": "mesa_bryce",
    "category": "mesa",
    "temperature": 2,
    "has_percipitation": false,
    "dimension": "overworld",
    "displayName": "mesa_bryce",
    "color": 1352389
  },
  {
    "id": 56,
    "name": "mesa_plateau",
    "category": "mesa",
    "temperature": 2,
    "has_percipitation": false,
    "dimension": "overworld",
    "displayName": "mesa_plateau",
    "color": 5603486
  },
  {
    "id": 57,
    "name": "mesa_plateau_mutated",
    "category": "mesa",
    "temperature": 2,
    "has_percipitation": false,
    "dimension": "overworld",
    "displayName": "mesa_plateau_mutated",
    "color": 5603486
  },
  {
    "id": 58,
    "name": "mesa_plateau_stone",
    "category": "mesa",
    "temperature": 2,
    "has_percipitation": false,
    "dimension": "overworld",
    "displayName": "mesa_plateau_stone",
    "color": 5603486
  },
  {
    "id": 59,
    "name": "mesa_plateau_stone_mutated",
    "category": "mesa",
    "temperature": 2,
    "has_percipitation": false,
    "dimension": "overworld",
    "displayName": "mesa_plateau_stone_mutated",
    "color": 5603486
  },
  {
    "id": 60,
    "name": "mushroom_island",
    "category": "mooshroom_island",
    "temperature": 0.8999999761581421,
    "has_percipitation": true,
    "dimension": "overworld",
    "displayName": "mushroom_island",
    "color": 9079191
  },
  {
    "id": 61,
    "name": "mushroom_island_shore",
    "category": "mooshroom_island",
    "temperature": 0.8999999761581421,
    "has_percipitation": true,
    "dimension": "overworld",
    "displayName": "mushroom_island_shore",
    "color": 8487315
  },
  {
    "id": 62,
    "name": "ocean",
    "category": "ocean",
    "temperature": 0.5,
    "has_percipitation": true,
    "dimension": "overworld",
    "displayName": "ocean",
    "color": 1542100
  },
  {
    "id": 63,
    "name": "pale_garden",
    "category": "overworld",
    "temperature": 0.699999988079071,
    "has_percipitation": true,
    "dimension": "overworld",
    "displayName": "pale_garden",
    "color": 6338559
  },
  {
    "id": 64,
    "name": "plains",
    "category": "overworld",
    "temperature": 0.800000011920929,
    "has_percipitation": true,
    "dimension": "overworld",
    "displayName": "plains",
    "color": 4501493
  },
  {
    "id": 65,
    "name": "redwood_taiga_hills_mutated",
    "category": "forest",
    "temperature": 0.30000001192092896,
    "has_percipitation": true,
    "dimension": "overworld",
    "displayName": "redwood_taiga_hills_mutated",
    "color": 2646904
  },
  {
    "id": 66,
    "name": "redwood_taiga_mutated",
    "category": "forest",
    "temperature": 0.25,
    "has_percipitation": true,
    "dimension": "overworld",
    "displayName": "redwood_taiga_mutated",
    "color": 2977143
  },
  {
    "id": 67,
    "name": "river",
    "category": "overworld",
    "temperature": 0.5,
    "has_percipitation": true,
    "dimension": "overworld",
    "displayName": "river",
    "color": 34047
  },
  {
    "id": 68,
    "name": "roofed_forest",
    "category": "forest",
    "temperature": 0.699999988079071,
    "has_percipitation": true,
    "dimension": "overworld",
    "displayName": "roofed_forest",
    "color": 3894481
  },
  {
    "id": 69,
    "name": "roofed_forest_mutated",
    "category": "forest",
    "temperature": 0.699999988079071,
    "has_percipitation": true,
    "dimension": "overworld",
    "displayName": "roofed_forest_mutated",
    "color": 3894481
  },
  {
    "id": 70,
    "name": "savanna",
    "category": "overworld",
    "temperature": 1.2000000476837158,
    "has_percipitation": false,
    "dimension": "overworld",
    "displayName": "savanna",
    "color": 2919324
  },
  {
    "id": 71,
    "name": "savanna_mutated",
    "category": "mutated",
    "temperature": 2,
    "has_percipitation": true,
    "dimension": "overworld",
    "displayName": "savanna_mutated",
    "color": 6338559
  },
  {
    "id": 72,
    "name": "savanna_plateau",
    "category": "overworld",
    "temperature": 1,
    "has_percipitation": false,
    "dimension": "overworld",
    "displayName": "savanna_plateau",
    "color": 2461864
  },
  {
    "id": 73,
    "name": "savanna_plateau_mutated",
    "category": "mutated",
    "temperature": 1,
    "has_percipitation": true,
    "dimension": "overworld",
    "displayName": "savanna_plateau_mutated",
    "color": 6338559
  },
  {
    "id": 74,
    "name": "snowy_slopes",
    "category": "mountains",
    "temperature": -0.30000001192092896,
    "has_percipitation": true,
    "dimension": "overworld",
    "displayName": "snowy_slopes",
    "color": 6338559
  },
  {
    "id": 75,
    "name": "soulsand_valley",
    "category": "nether",
    "temperature": 2,
    "has_percipitation": false,
    "dimension": "nether",
    "displayName": "soulsand_valley",
    "color": 9460055
  },
  {
    "id": 76,
    "name": "stone_beach",
    "category": "beach",
    "temperature": 0.20000000298023224,
    "has_percipitation": true,
    "dimension": "overworld",
    "displayName": "stone_beach",
    "color": 878523
  },
  {
    "id": 77,
    "name": "stony_peaks",
    "category": "mountains",
    "temperature": 1,
    "has_percipitation": true,
    "dimension": "overworld",
    "displayName": "stony_peaks",
    "color": 6338559
  },
  {
    "id": 78,
    "name": "sunflower_plains",
    "category": "mutated",
    "temperature": 0.800000011920929,
    "has_percipitation": true,
    "dimension": "overworld",
    "displayName": "sunflower_plains",
    "color": 6338559
  },
  {
    "id": 79,
    "name": "swampland",
    "category": "overworld",
    "temperature": 0.800000011920929,
    "has_percipitation": true,
    "dimension": "overworld",
    "displayName": "swampland",
    "color": 5006681
  },
  {
    "id": 80,
    "name": "swampland_mutated",
    "category": "mutated",
    "temperature": 0.800000011920929,
    "has_percipitation": true,
    "dimension": "overworld",
    "displayName": "swampland_mutated",
    "color": 5006681
  },
  {
    "id": 81,
    "name": "taiga",
    "category": "forest",
    "temperature": 0.25,
    "has_percipitation": true,
    "dimension": "overworld",
    "displayName": "taiga",
    "color": 2650242
  },
  {
    "id": 82,
    "name": "taiga_hills",
    "category": "hills",
    "temperature": 0.25,
    "has_percipitation": true,
    "dimension": "overworld",
    "displayName": "taiga_hills",
    "color": 2319747
  },
  {
    "id": 83,
    "name": "taiga_mutated",
    "category": "forest",
    "temperature": 0.25,
    "has_percipitation": true,
    "dimension": "overworld",
    "displayName": "taiga_mutated",
    "color": 1993602
  },
  {
    "id": 84,
    "name": "the_end",
    "category": "the_end",
    "temperature": 0.5,
    "has_percipitation": false,
    "dimension": "the_end",
    "displayName": "the_end",
    "color": 6443678
  },
  {
    "id": 85,
    "name": "warm_ocean",
    "category": "ocean",
    "temperature": 0.5,
    "has_percipitation": true,
    "dimension": "overworld",
    "displayName": "warm_ocean",
    "color": 176357
  },
  {
    "id": 86,
    "name": "warped_forest",
    "category": "nether",
    "temperature": 2,
    "has_percipitation": false,
    "dimension": "nether",
    "displayName": "warped_forest",
    "color": 9460055
  }
]