[
  {
    "name": "followRange",
    "resource": "generic.follow_range",
    "default": 32,
    "min": 0,
    "max": 2048
  },
  {
    "name": "knockbackResistance",
    "resource": "generic.knockback_resistance",
    "default": 0,
    "min": 0,
    "max": 1
  },
  {
    "name": "movementSpeed",
    "resource": "generic.movement_speed",
    "default": 0.7,
    "min": 0,
    "max": 1024
  },
  {
    "name": "attackDamage",
    "resource": "generic.attack_damage",
    "default": 2,
    "min": 0,
    "max": 2048
  },
  {
    "name": "horseJumpStrength",
    "resource": "horse.jump_strength",
    "default": 0.7,
    "min": 0,
    "max": 2
  },
  {
    "name": "zombieSpawnReinforcements",
    "resource": "zombie.spawn_reinforcements",
    "default": 0,
    "min": 0,
    "max": 1
  },
  {
    "name": "flyingSpeed",
    "resource": "generic.flying_speed",
    "default": 0.4,
    "min": 0,
    "max": 1024
  },
  {
    "name": "luck",
    "resource": "generic.luck",
    "default": 0,
    "min": -1024,
    "max": 1024
  },
  {
    "name": "health",
    "resource": "health",
    "default": 20,
    "min": 0,
    "max": 20
  },
  {
    "name": "absorption",
    "resource": "absorption",
    "default": 0,
    "min": 0,
    "max": 1024
  },
  {
    "name": "exhaustion",
    "resource": "player.exhaustion",
    "default": 0,
    "min": 0,
    "max": 5
  },
  {
    "name": "experienceProgress",
    "resource": "player.experience",
    "default": 0,
    "min": 0,
    "max": 1
  },
  {
    "name": "experienceLevel",
    "resource": "player.level",
    "default": 0,
    "min": 0,
    "max": 24791
  },
  {
    "name": "hunger",
    "resource": "player.hunger",
    "default": 20,
    "min": 0,
    "max": 20
  },
  {
    "name": "saturation",
    "resource": "player.saturation",
    "default": 20,
    "min": 0,
    "max": 20
  }
]